labfis/__init__.py
labfis/uncertainty.py
labfis/test/__init__.py
labfis/test/accuracy_test.py
labfis/test/arithmetic_test.py
labfis/test/interface_test.py
labfis-1.2.1.dist-info/AUTHORS
labfis-1.2.1.dist-info/LICENSE
labfis-1.2.1.dist-info/METADATA
labfis-1.2.1.dist-info/WHEEL
labfis-1.2.1.dist-info/top_level.txt
labfis-1.2.1.dist-info/RECORD
