Metadata-Version: 2.1
Name: labfis
Version: 1.2.1
Summary: Adds a new float type with uncertainty
Home-page: https://github.com/phisgroup/labfis.py
Author: Hendrik Dumith Louzada, João Carlos Rodrigues Júnior
Author-email: hendriklouzada@gmail.com, jc.rodrigues1997@usp.br
License: MIT
Download-URL: https://pypi.org/project/labfis/
Platform: UNKNOWN
Classifier: Development Status :: 5 - Production/Stable
Classifier: Intended Audience :: Education
Classifier: Intended Audience :: Science/Research
Classifier: Intended Audience :: End Users/Desktop
Classifier: Intended Audience :: Developers
Classifier: Operating System :: Microsoft :: Windows
Classifier: Operating System :: POSIX
Classifier: License :: OSI Approved :: MIT License
Classifier: Programming Language :: Python :: 3
Classifier: Programming Language :: Python :: 3.8
Requires-Python: >=3.7
